omok/__init__.py
omok/__main__.py
omok/agent.py
omok/env.py
omok/game.py
omok/transforms.py
omok/version.py
omok-0.0.11.dist-info/LICENSE
omok-0.0.11.dist-info/METADATA
omok-0.0.11.dist-info/WHEEL
omok-0.0.11.dist-info/top_level.txt
omok-0.0.11.dist-info/RECORD
